odoo/addons/mail_extra_header/README.rst
odoo/addons/mail_extra_header/__init__.py
odoo/addons/mail_extra_header/__manifest__.py
odoo/addons/mail_extra_header/i18n/it.po
odoo/addons/mail_extra_header/i18n/mail_extra_header.pot
odoo/addons/mail_extra_header/models/__init__.py
odoo/addons/mail_extra_header/models/ir_mail_server.py
odoo/addons/mail_extra_header/readme/CONFIGURE.md
odoo/addons/mail_extra_header/readme/CONTRIBUTORS.md
odoo/addons/mail_extra_header/readme/DESCRIPTION.md
odoo/addons/mail_extra_header/static/description/icon.png
odoo/addons/mail_extra_header/static/description/index.html
odoo/addons/mail_extra_header/tests/__init__.py
odoo/addons/mail_extra_header/tests/test_mail_extra_header.py
odoo/addons/mail_extra_header/views/ir_mail_server.xml
odoo_addon_mail_extra_header-18.0.1.0.0.4.dist-info/METADATA
odoo_addon_mail_extra_header-18.0.1.0.0.4.dist-info/WHEEL
odoo_addon_mail_extra_header-18.0.1.0.0.4.dist-info/top_level.txt
odoo_addon_mail_extra_header-18.0.1.0.0.4.dist-info/RECORD
