Metadata-Version: 2.1
Name: odoo-addon-mail_extra_header
Version: 18.0.1.0.0.4
Requires-Python: >=3.10
Requires-Dist: odoo==18.0.*
Summary: Adds extra headers per mail server to sent mails.
Home-page: https://github.com/OCA/mail
License: AGPL-3
Author: Odoo Community Association (OCA), Camptocamp
Author-email: support@odoo-community.org
Classifier: Programming Language :: Python
Classifier: Framework :: Odoo
Classifier: Framework :: Odoo :: 18.0
Classifier: License :: OSI Approved :: GNU Affero General Public License v3
